J_K FF/design.sv
module DFF(J, K, clk, Q);
  input J, K ; 
  input clk; 
  output reg Q; 
  
  always @(clk) 
    begin
      case ({J, K})
       
        2'b00:
        
          Q <= Q ;
        
        
        2'b01:
        
          Q <= 0 ;
        
        
        
        2'b10:
        begin
          Q <= 1 ;
        end
        
        
        2'b11:
        begin
          Q <= ~Q ;
        end
      endcase
    end 
  
endmodule

J_K FF/testbench.sv
module tb_DFF();
  reg J , K;
  reg clk;
  wire Q;
  
  DFF dut(J,K,clk,Q);
  
  
  initial begin
    clk=1;
    $monitor("Time = %2d,%b,%b,%b",$time,J,K,Q);
    forever #10 clk = ~clk;  
    
    end 
  
  initial begin 
    
    $dumpfile("dump.vcd"); $dumpvars; 
    
    
    J <= 0; 
    K <= 0; 
    #20;
    
    J <= 0; 
    K <= 1; 
    #20;
        
    J <= 1; 
    K <= 0; 
    #20;
        
    J <= 1; 
    K <= 1; 
    #20;
    
    
    $finish;
    
    end 
  
  
endmodule

J_K FF/dump.vcd
$date
	Fri Oct 22 02:48:08 2021
$end
$version
	Icarus Verilog
$end
$timescale
	1s
$end
$scope module tb_DFF $end
$var wire 1 ! Q $end
$var reg 1 " J $end
$var reg 1 # K $end
$var reg 1 $ clk $end
$scope module dut $end
$var wire 1 % J $end
$var wire 1 & K $end
$var wire 1 ' clk $end
$var reg 1 ( Q $end
$upscope $end
$upscope $end
$enddefinitions $end
#0
$dumpvars
x(
1'
0&
0%
1$
0#
0"
x!
$end
#10
0$
0'
#20
1#
1&
1$
1'
#30
0(
0!
0$
0'
#40
0#
0&
1"
1%
1$
1'
#50
1(
1!
0$
0'
#60
1#
1&
1$
1'
#70
0(
0!
0$
0'
#80
1(
1!
1$
1'
