seq/design.sv
// Code your design here
module seq(a,i,y,o);
  input [2:0]a;
  output [2:0]y;
  input i;
  output o;
  assign y[2] = i & ((a[2]&(~a[1])&(~a[0]) ) | (~a[2]&(a[1])&(a[0])) );
  assign y[1] = (i&(~a[2])) & ( a[1] ^ a[0]);
  assign y[0] = i & (~a[2]) & (~a[0]) ;
  assign o = i & (a[2]) & (~a[1]) & (~a[0]) ;
endmodule

seq/testbench.sv
// Code your testbench here
// or browse Examples
module TENC;
  reg [2:0]ta;
  reg ti;
  wire to;
  wire [2:0]ty;
  integer j;
  
  seq dut(.i(ti), .o(to), .y(ty), .a(ta));
  
  initial
    begin
      $monitor("Time = %2d,%b,%b,%b,%b,%b,%b,%b,%b",
               $time,ti,ta[2],ta[1],ta[0],ty[2],ty[1],ty[0],to);
      $dumpfile("dump.vcd"); $dumpvars;
      for (j=0; j<5; j=j+1)
        begin
          {ti,ta[2],ta[1],ta[0]}=j;
          #5;
        end
      for (j=8; j<13; j=j+1)
        begin
          {ti,ta[2],ta[1],ta[0]}=j;
          #5;
        end
      $finish;
    end 
endmodule

seq/dump.vcd
$date
	Fri Oct 22 02:47:12 2021
$end
$version
	Icarus Verilog
$end
$timescale
	1s
$end
$scope module TENC $end
$var wire 1 ! to $end
$var wire 3 " ty [2:0] $end
$var integer 32 # j [31:0] $end
$var reg 3 $ ta [2:0] $end
$var reg 1 % ti $end
$scope module dut $end
$var wire 3 & a [2:0] $end
$var wire 1 ' i $end
$var wire 1 ! o $end
$var wire 3 ( y [2:0] $end
$upscope $end
$upscope $end
$enddefinitions $end
#0
$dumpvars
b0 (
0'
b0 &
0%
b0 $
b0 #
b0 "
0!
$end
#5
b1 $
b1 &
b1 #
#10
b10 $
b10 &
b10 #
#15
b11 $
b11 &
b11 #
#20
b100 $
b100 &
b100 #
#25
b1 "
b1 (
1%
1'
b0 &
b0 $
b1000 #
#30
b10 "
b10 (
b1 $
b1 &
b1001 #
#35
b11 "
b11 (
b10 $
b10 &
b1010 #
#40
b100 "
b100 (
b11 $
b11 &
b1011 #
#45
1!
b100 "
b100 (
b100 $
b100 &
b1100 #
#50
b1101 #
