MUX/design.sv
// Code your design here
module MUX(s1,s2,i1,i2,i3,i4,y);
  input s1,s2,i1,i2,i3,i4;
  output y;
  
  //STRUCTURAL
  
  /*
  wire w1,w2,w3,w4,n1,n2;
  not(n1,s1);
  not(n2,s2);
  and(w1,i1,n1,n2);
  and(w2,i2,n1,s2);
  and(w3,i3,s1,n2);
  and(w4,i4,s1,s2);
  or(y,w1,w2,w3,w4);
  */
  
  //DATA FLOW
  
  /*
  assign y = (((~s2) & (~s1) & i1)| ( (~s1) & s2 & i2)|(s1 & (~s2) & i3)|(s2 & s1 & i4));
  */
  
  //BEHAVIOURAL
  
  
  reg y;
  always @ (s1 or s2 or i1 or i2 or i3 or i4)
    begin
      y = (((~s2) & (~s1) & i1)| ( (~s1) & s2 & i2)|(s1 &       		(~s2) & i3)|(s2 & s1 & i4));
    end
  
  
endmodule

MUX/testbench.sv
// Code your testbench here
// or browse Examples
module tmux;
  reg ts1,ts2,t1,t2,t3,t4;
  wire ty;
  integer i;
  integer j;
  MUX uut(.s1(ts1), .s2(ts2), .i1(t1), .i2(t2), .i3(t3), .i4(t4), .y(ty));
  initial
    begin
      $monitor("Time = %2d,%b,%b,%b,%b,%b,%b,%b",
               $time,ts1,ts2,t1,t2,t3,t4,ty);
      $dumpfile("dump.vcd"); $dumpvars;
      for(j=0; j<4; j=j+1)
       begin
         {t4,t3,t2,t1}=2**j;
           for (i=0; i<4; i=i+1)
            begin
              {ts1,ts2}=i;
            #5;
           end
       end
      $finish;
    end
endmodule

MUX/dump.vcd
$date
	Fri Oct 22 02:38:23 2021
$end
$version
	Icarus Verilog
$end
$timescale
	1s
$end
$scope module tmux $end
$var wire 1 ! ty $end
$var integer 32 " i [31:0] $end
$var integer 32 # j [31:0] $end
$var reg 1 $ t1 $end
$var reg 1 % t2 $end
$var reg 1 & t3 $end
$var reg 1 ' t4 $end
$var reg 1 ( ts1 $end
$var reg 1 ) ts2 $end
$scope module uut $end
$var wire 1 * i1 $end
$var wire 1 + i2 $end
$var wire 1 , i3 $end
$var wire 1 - i4 $end
$var wire 1 . s1 $end
$var wire 1 / s2 $end
$var reg 1 0 y $end
$upscope $end
$upscope $end
$enddefinitions $end
#0
$dumpvars
10
0/
0.
0-
0,
0+
1*
0)
0(
0'
0&
0%
1$
b0 #
b0 "
1!
$end
#5
00
0!
1)
1/
b1 "
#10
1(
1.
0)
0/
b10 "
#15
1)
1/
b11 "
#20
0(
0.
0)
0/
1%
1+
0$
0*
b1 #
b0 "
#25
10
1!
1)
1/
b1 "
#30
00
0!
1(
1.
0)
0/
b10 "
#35
1)
1/
b11 "
#40
0(
0.
0)
0/
1&
1,
0%
0+
b10 #
b0 "
#45
1)
1/
b1 "
#50
10
1!
1(
1.
0)
0/
b10 "
#55
00
0!
1)
1/
b11 "
#60
0(
0.
0)
0/
1'
1-
0&
0,
b11 #
b0 "
#65
1)
1/
b1 "
#70
1(
1.
0)
0/
b10 "
#75
10
1!
1)
1/
b11 "
#80
b100 #
b100 "
