full sub/design.sv
// Code your design here
module FS(a,b,c,d,br);
  input a,b,c;
  output d,br;
  
  //structural
   
  /*
  wire w1,w2,w3,w4,w5;
  xor(w1,a,b);
  xor(d,w1,c);
  not(w2,w1);
  and(w3,w2,c);
  not(w4,a);
  and(w5,w4,b);
  or(br,w5,w3);
  */
  
  //Data Flow
  
  /*
  assign d = (a^b)^c;
  assign br = (~(a^b)&c)|(~a&b);
  */
  
  //Behavioral
  
  reg d,br;
  always @ (a or b or c)
    begin
      d = (a^b)^c;
      br = (~(a^b)&c)|(~a&b);
    end
  
endmodule

full sub/testbench.sv
// Code your testbench here
// or browse Examples
module FS_TB;
  reg ta,tb,tc;
  wire td,tbr;
  integer i;
  
  FS uut(.a(ta), .b(tb), .c(tc), .d(td), .br(tbr));
  
  initial
    begin
      $monitor("Time = %2d,%b,%b,%b,%b,%b",$time,ta,tb,tc,td,tbr);
      $dumpfile("dump.vcd"); $dumpvars;
      
      for (i=0; i<8; i=i+1)
        begin
          {ta, tb, tc} = i;
          #5;
        end
      $finish;
    end
endmodule

full sub/dump.vcd
$date
	Fri Oct 22 02:37:06 2021
$end
$version
	Icarus Verilog
$end
$timescale
	1s
$end
$scope module FS_TB $end
$var wire 1 ! tbr $end
$var wire 1 " td $end
$var integer 32 # i [31:0] $end
$var reg 1 $ ta $end
$var reg 1 % tb $end
$var reg 1 & tc $end
$scope module uut $end
$var wire 1 ' a $end
$var wire 1 ( b $end
$var wire 1 ) c $end
$var reg 1 * br $end
$var reg 1 + d $end
$upscope $end
$upscope $end
$enddefinitions $end
#0
$dumpvars
0+
0*
0)
0(
0'
0&
0%
0$
b0 #
0"
0!
$end
#5
1*
1!
1+
1"
1&
1)
b1 #
#10
1%
1(
0&
0)
b10 #
#15
0+
0"
1&
1)
b11 #
#20
0*
0!
1+
1"
1$
1'
0%
0(
0&
0)
b100 #
#25
0+
0"
1&
1)
b101 #
#30
1%
1(
0&
0)
b110 #
#35
1*
1!
1+
1"
1&
1)
b111 #
#40
b1000 #
