midsem/design.sv
module FS (A, B, C, D, Bo);
  input A, B, C;
  output D, Bo;
  assign Bo = (B & C) | ( ( ~A ) & ( B ^ C ) ) ;
  assign D  = ( A ^ ( B ^ C ) ) ;
endmodule

midsem/testbench.sv
module TB_FS;
  reg ta, tb, tc;
  wire td, tbo;
  integer i;
  FS dut(.A(ta), .B(tb), .C(tc), .D(td), .Bo(tbo));
  initial
    begin
      $monitor("time @ %2d- ip %b %b %b - op %b %b", $time, ta, tb, tc, tbo, td );
      $dumpfile("dump.vcd");
      $dumpvars;
      for ( i = 0 ; i < 8 ; i = i+1 )
      begin
        {ta, tb, tc } = i ;
        #5;
      end
      $finish;
    end
endmodule

midsem/dump.vcd
$date
	Fri Oct 22 02:46:04 2021
$end
$version
	Icarus Verilog
$end
$timescale
	1s
$end
$scope module TB_FS $end
$var wire 1 ! tbo $end
$var wire 1 " td $end
$var integer 32 # i [31:0] $end
$var reg 1 $ ta $end
$var reg 1 % tb $end
$var reg 1 & tc $end
$scope module dut $end
$var wire 1 ' A $end
$var wire 1 ( B $end
$var wire 1 ! Bo $end
$var wire 1 ) C $end
$var wire 1 " D $end
$upscope $end
$upscope $end
$enddefinitions $end
#0
$dumpvars
0)
0(
0'
0&
0%
0$
b0 #
0"
0!
$end
#5
1!
1"
1&
1)
b1 #
#10
1%
1(
0&
0)
b10 #
#15
0"
1&
1)
b11 #
#20
0!
1"
1$
1'
0%
0(
0&
0)
b100 #
#25
0"
1&
1)
b101 #
#30
1%
1(
0&
0)
b110 #
#35
1!
1"
1&
1)
b111 #
#40
b1000 #
